{
  "bundler": "rollup",
  "shimport": "2.0.4",
  "assets": {
    "main": "client.cd23e932.js"
  },
  "css": {
    "main": [
      "client-ee649a9f.css"
    ]
  },
  "dependencies": {
    "index.svelte": [
      "index.41f8c325.js",
      "trinity-thumb.998df228.js",
      "inject_styles.5607aec6.js",
      "trinity-thumb-aa0f8620.css",
      "index-de894aa9.css"
    ],
    "experience.svelte": [
      "experience.ab6482ee.js",
      "inject_styles.5607aec6.js",
      "experience-e57a5e76.css"
    ],
    "projects/goosehead-insurance.svelte": [
      "goosehead-insurance.9568597e.js",
      "PageTitle.12abd4c9.js",
      "ProjectDetailTemplate.d09a964b.js",
      "inject_styles.5607aec6.js",
      "PageTitle-fb9837a7.css",
      "ProjectDetailTemplate-366f6067.css",
      "goosehead-insurance-8ea4d199.css"
    ],
    "projects/trinity-consultants.svelte": [
      "trinity-consultants.79ae3676.js",
      "PageTitle.12abd4c9.js",
      "ProjectDetailTemplate.d09a964b.js",
      "inject_styles.5607aec6.js",
      "PageTitle-fb9837a7.css",
      "ProjectDetailTemplate-366f6067.css"
    ],
    "projects/creative-revolt.svelte": [
      "creative-revolt.022d5fb0.js",
      "PageTitle.12abd4c9.js",
      "ProjectDetailTemplate.d09a964b.js",
      "inject_styles.5607aec6.js",
      "PageTitle-fb9837a7.css",
      "ProjectDetailTemplate-366f6067.css"
    ],
    "projects/university-park.svelte": [
      "university-park.8518a7a1.js",
      "PageTitle.12abd4c9.js",
      "ProjectDetailTemplate.d09a964b.js",
      "inject_styles.5607aec6.js",
      "PageTitle-fb9837a7.css",
      "ProjectDetailTemplate-366f6067.css"
    ],
    "projects/di-repairs.svelte": [
      "di-repairs.44355b3f.js",
      "PageTitle.12abd4c9.js",
      "ProjectDetailTemplate.d09a964b.js",
      "inject_styles.5607aec6.js",
      "PageTitle-fb9837a7.css",
      "ProjectDetailTemplate-366f6067.css"
    ],
    "projects/stallion.svelte": [
      "stallion.5dac1efa.js",
      "PageTitle.12abd4c9.js",
      "ProjectDetailTemplate.d09a964b.js",
      "inject_styles.5607aec6.js",
      "PageTitle-fb9837a7.css",
      "ProjectDetailTemplate-366f6067.css"
    ],
    "projects/halcyon.svelte": [
      "halcyon.d81d565c.js",
      "PageTitle.12abd4c9.js",
      "ProjectDetailTemplate.d09a964b.js",
      "inject_styles.5607aec6.js",
      "PageTitle-fb9837a7.css",
      "ProjectDetailTemplate-366f6067.css"
    ],
    "projects.svelte": [
      "projects.7eefb3f2.js",
      "trinity-thumb.998df228.js",
      "PageTitle.12abd4c9.js",
      "inject_styles.5607aec6.js",
      "trinity-thumb-aa0f8620.css",
      "PageTitle-fb9837a7.css",
      "projects-a7f6164d.css"
    ],
    "about.svelte": [
      "about.da38af08.js",
      "inject_styles.5607aec6.js",
      "about-e2baa763.css"
    ]
  },
  "legacy_assets": {
    "main": "client.4457c9f7.js"
  }
}